LICENSE
MANIFEST.in
README.rst
reparser.py
setup.py
ReParser.egg-info/PKG-INFO
ReParser.egg-info/SOURCES.txt
ReParser.egg-info/dependency_links.txt
ReParser.egg-info/requires.txt
ReParser.egg-info/top_level.txt