Metadata-Version: 1.1
Name: ReParser
Version: 1.4.2
Summary: Simple regex-based lexer/parser for inline markup
Home-page: https://github.com/xmikos/reparser
Author: Michal Krenek (Mikos)
Author-email: m.krenek@gmail.com
License: MIT
Platform: UNKNOWN
Classifier: Development Status :: 4 - Beta
Classifier: Intended Audience :: Developers
Classifier: License :: OSI Approved :: MIT License
Classifier: Natural Language :: English
Classifier: Operating System :: OS Independent
Classifier: Programming Language :: Python :: 3
Classifier: Topic :: Software Development :: Libraries :: Python Modules
Classifier: Topic :: Text Processing :: Markup
